mask_framework_lib/__init__.py
mask_framework_lib/Dictionaries/__init__.py
mask_framework_lib/masking_plugins/Mask_abstract.py
mask_framework_lib/masking_plugins/Mask_date_simple.py
mask_framework_lib/masking_plugins/Mask_names_simple.py
mask_framework_lib/masking_plugins/__init__.py
mask_framework_lib/masking_plugins/mask_firstname_randomized.py
mask_framework_lib/masking_plugins/mask_job_randomized.py
mask_framework_lib/masking_plugins/mask_lastname_randomized.py
mask_framework_lib/masking_plugins/mask_ohip_randomized.py
mask_framework_lib/masking_plugins/mask_phone_randomized.py
mask_framework_lib/masking_plugins/mask_redact.py
mask_framework_lib/masking_plugins/mask_zipcode_randomized.py
mask_framework_lib/masking_plugins/mask_zipcode_simple.py
mask_framework_lib/masking_plugins/populate.py
mask_framework_lib/ner_plugins/NER_BiLSTM_ELMo_i2b2.py
mask_framework_lib/ner_plugins/NER_BiLSTM_Glove_i2b2.py
mask_framework_lib/ner_plugins/NER_CRF.py
mask_framework_lib/ner_plugins/NER_CRF_dictionaries.py
mask_framework_lib/ner_plugins/NER_CRF_dictionaries_pycrfsuite.py
mask_framework_lib/ner_plugins/NER_CRF_python_crfsuite.py
mask_framework_lib/ner_plugins/NER_abstract.py
mask_framework_lib/ner_plugins/__init__.py
mask_framework_lib/ner_plugins/utils/__init__.py
mask_framework_lib/ner_plugins/utils/readers.py
mask_framework_lib/ner_plugins/utils/spec_tokenizers.py
Mask_anonymization_framework-1.3.2.dist-info/LICENSE
Mask_anonymization_framework-1.3.2.dist-info/METADATA
Mask_anonymization_framework-1.3.2.dist-info/NOTICE
Mask_anonymization_framework-1.3.2.dist-info/WHEEL
Mask_anonymization_framework-1.3.2.dist-info/top_level.txt
Mask_anonymization_framework-1.3.2.dist-info/RECORD
