Metadata-Version: 2.1
Name: Mask-anonymization-framework
Version: 1.3.2
Summary: Anonymization of clinical texts
Home-page: https://github.com/nikolamilosevic86/mask
Author: University of Manchester & ICES
Author-email: nikola.milosevic86@gmail.com
Project-URL: Bug Tracker, https://github.com/nikolamilosevic86/mask/issues
Classifier: Programming Language :: Python :: 3
Classifier: License :: OSI Approved :: GNU General Public License v3 or later (GPLv3+)
Classifier: Operating System :: OS Independent
Classifier: Programming Language :: Python :: 3
Classifier: Programming Language :: Python :: 3.4
Classifier: Programming Language :: Python :: 3.5
Classifier: Programming Language :: Python :: 3.6
Requires-Python: >=3.6
License-File: LICENSE
License-File: NOTICE
Requires-Dist: tensorflow
Requires-Dist: python-crfsuite (==0.9.6)
Requires-Dist: tqdm (==4.34.0)
Requires-Dist: sphinx-rtd-theme (==0.4.*)
Requires-Dist: nltk (>=3.4.5)
Requires-Dist: numpy (==1.17.0)
Requires-Dist: scikit-learn (==0.21.3)
Requires-Dist: sklearn-crfsuite (==0.3.6)
Requires-Dist: Sphinx (==1.8.5)
Requires-Dist: attrs (==19.1.0)
Requires-Dist: pytest (==5.1.1)
Requires-Dist: Keras (==2.2.5)
